MANIFEST.in
README.rst
setup.py
levit_utils/__init__.py
levit_utils/admin.py
levit_utils/context_processors.py
levit_utils/db.py
levit_utils/fields.py
levit_utils/middleware.py
levit_utils/models.py
levit_utils/states.py
levit_utils/tests.py
levit_utils/views.py
levit_utils.egg-info/PKG-INFO
levit_utils.egg-info/SOURCES.txt
levit_utils.egg-info/dependency_links.txt
levit_utils.egg-info/requires.txt
levit_utils.egg-info/top_level.txt
levit_utils/templatetags/__init__.py
levit_utils/templatetags/levit_utils.py